iteriotools/__init__.py
iteriotools-0.0.4.dist-info/LICENSE
iteriotools-0.0.4.dist-info/METADATA
iteriotools-0.0.4.dist-info/WHEEL
iteriotools-0.0.4.dist-info/top_level.txt
iteriotools-0.0.4.dist-info/RECORD
